kicksaw_integration_utils/__init__.py
kicksaw_integration_utils/aws/__init__.py
kicksaw_integration_utils/aws/sqs/__init__.py
kicksaw_integration_utils/aws/sqs/queue.py
kicksaw_integration_utils/csv_helpers.py
kicksaw_integration_utils/field_formatters.py
kicksaw_integration_utils/orchestrator.py
kicksaw_integration_utils/s3_helpers.py
kicksaw_integration_utils/salesforce_client.py
kicksaw_integration_utils/sfdc_helpers.py
kicksaw_integration_utils/sqs_helpers.py
kicksaw_integration_utils/step_function_helpers.py
kicksaw_integration_utils/utils.py
kicksaw_integration_utils-2.3.1.dist-info/WHEEL
kicksaw_integration_utils-2.3.1.dist-info/METADATA
kicksaw_integration_utils-2.3.1.dist-info/RECORD
