Metadata-Version: 2.1
Name: kicksaw-integration-utils
Version: 2.3.1
Summary: A set of helper functions for CSV to Salesforce procedures, with reporting in AWS S3
Home-page: https://github.com/Kicksaw-Consulting/kicksaw-integration-utils
Keywords: kicksaw,aws,s3,sqs,simple salesforce,csv
Author: Alex Drozd
Author-email: alex@kicksaw.com
Requires-Python: >=3.8,<4.0
Classifier: Programming Language :: Python :: 3
Classifier: Programming Language :: Python :: 3.8
Classifier: Programming Language :: Python :: 3.9
Classifier: Programming Language :: Python :: 3.10
Requires-Dist: boto3 (>=1.17.3,<2.0.0)
Requires-Dist: pydantic (>=1.9.0,<2.0.0)
Requires-Dist: simple-salesforce (>=1.10.1,<2.0.0)
Project-URL: Repository, https://github.com/Kicksaw-Consulting/kicksaw-integration-utils
